README.txt
bayescluster.py
setup.py
bayescluster/__init__.py
bayescluster/cluster.py
bayescluster/measures.py
bayescluster.egg-info/PKG-INFO
bayescluster.egg-info/SOURCES.txt
bayescluster.egg-info/dependency_links.txt
bayescluster.egg-info/requires.txt
bayescluster.egg-info/top_level.txt