Metadata-Version: 1.2
Name: bayescluster
Version: 1.0
Summary: A clustering package which uses bayesian methods and returns classifications and a tree structure
Home-page: https://github.com/mtw25/Stat663FinalProject-Matt_Yamac
Author: Matthew Welch, Yamac Isik
Author-email: matt.welch@duke.edu ,yamac.isik@duke.edu
License: MIT
Platform: UNKNOWN
Requires-Python: >=3
